dashing/__init__.py
dashing_next-0.1.0.dist-info/LICENSE
dashing_next-0.1.0.dist-info/WHEEL
dashing_next-0.1.0.dist-info/METADATA
dashing_next-0.1.0.dist-info/RECORD
