Metadata-Version: 2.1
Name: dashing-next
Version: 0.1.0
Summary: Dashing allows to quickly create terminal-based dashboards in Python.
Author-email: Federico Ceratto <federico@debian.org>
Classifier: Development Status :: 4 - Beta
Classifier: Environment :: Console
Classifier: Intended Audience :: Developers
Classifier: License :: OSI Approved :: GNU Lesser General Public License v3 (LGPLv3)
Requires-Dist: blessed~=1.20
Requires-Dist: black~=24.0 ; extra == "dev"
Requires-Dist: flake8~=7.0 ; extra == "dev"
Requires-Dist: pre-commit~=3.0 ; extra == "dev"
Requires-Dist: isort~=5.12 ; extra == "dev"
Requires-Dist: flake8-pyproject~=1.2 ; extra == "dev"
Requires-Dist: bump-my-version~=0.18 ; extra == "dev"
Project-URL: Home, https://github.com/FedericoCeratto/dashing
Provides-Extra: dev
